kloudy/__init__.py
kloudy/kloudy.py
kloudy/aws/commands/aws.py
kloudy/azure/commands/azure.py
kloudy/gcp/commands/gcp.py
kloudy-0.1.1.dist-info/LICENSE
kloudy-0.1.1.dist-info/METADATA
kloudy-0.1.1.dist-info/PKG-INFO 2
kloudy-0.1.1.dist-info/SOURCES 2.txt
kloudy-0.1.1.dist-info/WHEEL
kloudy-0.1.1.dist-info/dependency_links 2.txt
kloudy-0.1.1.dist-info/entry_points 2.txt
kloudy-0.1.1.dist-info/entry_points.txt
kloudy-0.1.1.dist-info/requires 2.txt
kloudy-0.1.1.dist-info/top_level 2.txt
kloudy-0.1.1.dist-info/top_level.txt
kloudy-0.1.1.dist-info/RECORD
