Metadata-Version: 2.1
Name: kloudy
Version: 0.1.1
Summary: kloudy - a human friendly command line utility for your cloud (AWS,GCP & Azure)
Home-page: https://github.com/sdevang/kloudy
Author: Dev Shah
Author-email: dev@awsninja.co.uk
License: UNKNOWN
Keywords: awscli kloudy gcpcli gcloud aws azure
Platform: UNKNOWN
Classifier: Intended Audience :: Developers
Classifier: Intended Audience :: System Administrators
Classifier: Intended Audience :: Education
Classifier: Intended Audience :: Information Technology
Classifier: Topic :: System :: Systems Administration
Classifier: License :: OSI Approved :: MIT License
Classifier: Operating System :: OS Independent
Classifier: Programming Language :: Python :: 3.6
Classifier: Programming Language :: Python :: 3.7
Classifier: Programming Language :: Python :: 3.8
Classifier: Development Status :: 3 - Alpha
Requires-Python: >=3.6
Requires-Dist: Click
Requires-Dist: boto3
Requires-Dist: requests
Requires-Dist: texttable
Requires-Dist: colorama
Requires-Dist: click-completion
Requires-Dist: oauth2client
Requires-Dist: google-api-python-client
Requires-Dist: azure
